kvax/__init__.py
kvax/ops/__init__.py
kvax/ops/flash_attention_cudnn.py
kvax/ops/flash_attention_triton.py
kvax/ops/mask_creator.py
kvax/utils/__init__.py
kvax/utils/benchmarking.py
kvax/utils/common.py
kvax/utils/math.py
kvax/utils/permutation.py
kvax/utils/sharding.py
kvax/utils/specs.py
kvax/utils/typing.py
kvax-0.1.0.dist-info/LICENSE
kvax-0.1.0.dist-info/METADATA
kvax-0.1.0.dist-info/NOTICE.md
kvax-0.1.0.dist-info/WHEEL
kvax-0.1.0.dist-info/top_level.txt
kvax-0.1.0.dist-info/RECORD
