Metadata-Version: 2.2
Name: kvax
Version: 0.1.0
Summary: Fast and easy-to-use implementation of flash attention.
Author-email: Sergei Skvortsov <sergeyskv@nebius.com>
License: 
Requires-Python: >=3.10
License-File: LICENSE
License-File: NOTICE.md
Requires-Dist: chex>=0.1.85
Requires-Dist: jax>=0.4.34
Requires-Dist: jax-triton>=0.2.0
Requires-Dist: triton>=3.1
Provides-Extra: dev
Requires-Dist: pre-commit>=4.0.1; extra == "dev"
Requires-Dist: pytest>=6.0; extra == "dev"
Requires-Dist: click>=8.1.3; extra == "dev"
